polars_cisco_umrella-0.2.0.dist-info/METADATA
polars_cisco_umrella-0.2.0.dist-info/WHEEL
polars_cisco_umrella/_internal.pyi
polars_cisco_umrella/typing.py
polars_cisco_umrella/__init__.py
polars_cisco_umrella/_internal.abi3.so
polars_cisco_umrella-0.2.0.dist-info/RECORD
