Metadata-Version: 2.4
Name: polars-cisco-umrella
Version: 0.2.0
Classifier: Programming Language :: Rust
Classifier: Programming Language :: Python :: Implementation :: CPython
Classifier: Programming Language :: Python :: Implementation :: PyPy
Requires-Dist: polars >=1.8.2
Requires-Python: >=3.8
